banner/__init__.py
banner/_version.py
banner/helpers.py
banner/main.py
banner/rfc.py
banner-0.0.2.dist-info/METADATA
banner-0.0.2.dist-info/RECORD
banner-0.0.2.dist-info/WHEEL
banner-0.0.2.dist-info/entry_points.txt
banner-0.0.2.dist-info/top_level.txt
