Metadata-Version: 1.0
Name: banner
Version: 0.0.2
Summary: banner is a tool for predicting microbiome labels based on hulk sketches
Home-page: http://will-rowe.github.io/
Author: Will Rowe
Author-email: will.rowe@stfc.ac.uk
License: MIT
Platform: UNKNOWN
